grit_guardian_cli/__init__.py
grit_guardian_cli/analytics/__init__.py
grit_guardian_cli/analytics/analytics.py
grit_guardian_cli/cli/__init__.py
grit_guardian_cli/cli/main.py
grit_guardian_cli/core/__init__.py
grit_guardian_cli/core/habit_tracker.py
grit_guardian_cli/core/models.py
grit_guardian_cli/guardian/__init__.py
grit_guardian_cli/guardian/guardian.py
grit_guardian_cli/guardian/messages.json
grit_guardian_cli/persistence/__init__.py
grit_guardian_cli/persistence/database_manager.py
grit_guardian_cli/ui/__init__.py
grit_guardian_cli/ui/messages.json
grit_guardian_cli/ui/ui.py
grit_guardian_cli-0.1.1a2.dist-info/LICENSE
grit_guardian_cli-0.1.1a2.dist-info/METADATA
grit_guardian_cli-0.1.1a2.dist-info/WHEEL
grit_guardian_cli-0.1.1a2.dist-info/entry_points.txt
grit_guardian_cli-0.1.1a2.dist-info/RECORD
